{
  "id": "generated-2026-07-17-shiseido-kose-ai-implementation",
  "title": "資生堂・コーセーがAIを現場実装―「期待7割・実利用1割」のギャップが埋まり始めた",
  "slug": "shiseido-kose-ai-implementation",
  "category": "trends",
  "excerpt": "資生堂は店頭端末「B-TAB」に生成AIチャットボット導入、コーセーはお客様相談室にAI横断検索「J-Insight」を導入。大手の現場実装が加速する一方、AI活用への「期待7割・実利用1割」というギャップが縮まり始めている。",
  "content": "「AIを検討している」段階から「AIを現場に入れた」段階へ。2026年、美容業界のAI活用は転換点を迎えた。\n\n## 資生堂のAI実装：研究開発から接客現場まで\n\n資生堂は複数のAIを段階的に実装している。美容部員向け店頭端末「B-TAB」には生成AIチャットボットを導入し、スタッフが顧客への商品説明や提案をAIのサポートで行える環境を整えた。研究開発領域では処方開発AI「VOYAGER」に続き、2026年3月には原料探索業務を2〜3時間から大幅短縮する原料探索AIエージェントを発表した。\n\n研究から接客まで一気通貫でAIを活用している点が資生堂の特徴だ。\n\n## コーセーのAI実装：顧客対応の横断検索\n\nコーセーはお客様相談室にAI横断検索「J-Insight」を導入した。複数の製品情報・成分情報・過去の問い合わせ対応履歴などを横断的に検索できる仕組みで、相談員の回答精度と速度を上げている。\n\nまたコーセーの「HADA mite」（AI肌診断・肌色分析・バーチャルメイク）はリニューアル後に利用者数が403.6%増加した実績もある。\n\n## 「期待7割・実利用1割」のギャップ\n\n「美容×AI利用実態調査2026」（電通マクロミルインサイト・アイスタイル共同調査）によると、美容商品購入時にAIを実際に活用している層は約1割にとどまる一方、「効率化に役立つ」と期待する層は7割以上に達する。\n\nこのギャップは今後急速に縮まると見られている。大手メーカーが現場実装を進めることで「AIを使った体験」が一般顧客にも広がり、サロン・ドラッグストア・EC全体でAI活用が標準化される流れになっている。\n\n## 中小サロンが今すぐ使えるAI\n\n大手のAI導入を横目に見ながら、中小サロンも動けるツールは増えている。\n\n- **AI予約システム**：月額3,000円前後から導入可能な24時間自動受付\n- **ARカラーシミュレーション**：来店前にヘアカラーのイメージを共有できる提案ツール\n- **チャットボット**：LINE公式や予約サイトへの問い合わせを自動対応\n\nどれも初期投資は少なく、まず試して合わなければ止めるという使い方ができる。\n\n## まとめ\n\n資生堂・コーセーの現場実装が示すのは、「AIは検討するものから使うもの」への移行だ。中小サロンも、月数千円から始められるAI予約・提案ツールを1つ試してみることが、数年後の競合との差をつくる第一歩になる。\n\n## 参考\n\n- 処方開発の時代へ！日本国内「AI×美容テック」2026最新動向（ヌーヴェル日本版）\n- 【2026年版】エステ・美容サロンのAI活用事例10選（ワムタイムズ）\n- NEXT BEAUTY JOURNAL週次レポート「美容業界最新レポート」2026年7月17日号",
  "thumbnail": "",
  "publishedAt": "2026-07-17",
  "author": "NEXT BEAUTY編集部",
  "tags": ["AI", "資生堂", "コーセー", "美容テック", "DX"]
}
